xerxes/__init__.py
xerxes/cli.py
xerxes/agent/__init__.py
xerxes/agent/core.py
xerxes/agent/prompts.py
xerxes/agent/session.py
xerxes/config/__init__.py
xerxes/config/settings.py
xerxes/executor/__init__.py
xerxes/executor/command.py
xerxes/executor/safety.py
xerxes/llm/__init__.py
xerxes/llm/base.py
xerxes/llm/vertex.py
xerxes/tools/__init__.py
xerxes/tools/base.py
xerxes/tools/registry.py
xerxes/tools/shell.py
xerxes/ui/__init__.py
xerxes/ui/keybindings.py
xerxes/ui/output.py
xerxes/ui/prompt.py
xerxes/utils/__init__.py
xerxes-0.3.0.dist-info/METADATA
xerxes-0.3.0.dist-info/WHEEL
xerxes-0.3.0.dist-info/entry_points.txt
xerxes-0.3.0.dist-info/licenses/LICENSE
xerxes-0.3.0.dist-info/RECORD
