Metadata-Version: 2.4
Name: xerxes
Version: 0.3.0
Summary: An intelligent agent with BYOK for managing cloud infrastructure & bash env
Author-email: Shammi Anand <shammianand101@gmail.com>
License: MIT
License-File: LICENSE
Keywords: agent,ai,aws,devops,docker,gcp,kubernetes,llm
Classifier: Development Status :: 3 - Alpha
Classifier: Intended Audience :: Developers
Classifier: License :: OSI Approved :: MIT License
Classifier: Programming Language :: Python :: 3.10
Classifier: Programming Language :: Python :: 3.11
Classifier: Programming Language :: Python :: 3.12
Requires-Python: >=3.10
Requires-Dist: google-cloud-aiplatform>=1.60.0
Requires-Dist: httpx>=0.27.0
Requires-Dist: prompt-toolkit>=3.0.0
Requires-Dist: pydantic-settings>=2.0.0
Requires-Dist: pydantic>=2.0.0
Requires-Dist: python-dotenv>=1.0.0
Requires-Dist: pyyaml>=6.0.0
Requires-Dist: rich>=13.0.0
Requires-Dist: typer>=0.12.0
Provides-Extra: dev
Requires-Dist: black>=24.0.0; extra == 'dev'
Requires-Dist: pytest-asyncio>=0.23.0; extra == 'dev'
Requires-Dist: pytest>=8.0.0; extra == 'dev'
Requires-Dist: ruff>=0.4.0; extra == 'dev'
